{
     "Contract Awarder": "Koperasi Warga Tentera Laut Perak Berhad (KWTLP)",
     "Contracted Services": [
          "Supply of goods"
     ],
     "Nature of Contract": [
          "One-off"
     ],
     "Collection Via": [
          "ePerolehan (eP)",
          "Electronic Funds Transfer (EFT)"
     ],
     "Contract Description": [
          "P-285755/1 - Spare for CWP Plant @ RM11,328.80",
          "P-287931/1 - Sanitary Systems-Transfer Pump A & B @ RM45,200.12",
          "P-289513/1 - K Item-Paint Roller-O0000000 Stock Project @ RM2,231.00",
          "P-289550/1 - Maintenance for Boat Seladang @ RM44,441.00",
          "P-289770/1 - Spares Maintenance Loc 32-TMR 214663 @ RM2,587.20",
          "P-289790/1 - Padlock for Substation-TMR 221587 @ RM2,019.60",
          "P-289830/1 - Replacement PCO Graphic Display @ 3,257.10",
          "P-290273/1 - Internal Hull & Outfitting - Loc 10 @ RM11,794.86",
          "P-290972/2 - Maintenance for Boat Seladang 1 & 2 (M) @ RM 950.40",
          "P-291273/1 - Toilet Bowl Seat and Cover TMR 223666 @ RM1,280.00"
     ],
     "Tenure of Contract": "Varies per item, ranging from 1/2 month to 3 1/2 months",
     "Delivery Period": [
          "21/7/2022 to 12/9/2023 - Delivered on 12/12/2022",
          "14/9/2022 to 31/12/2022 - Delivered on 11/10/2022",
          "17/10/2022 to 1/11/2022 - Delivered on 23/11/2022",
          "5/10/2022 to 23/11/2022 - Delivered on 16/11/2022",
          "17/10/2022 to 23/11/2022 - Delivered on 25/11/2022",
          "17/10/2022 to 7/11/2022 - Delivered on 14/12/2022",
          "19/10/2022 to 9/12/2022 - Delivered on 12/12/2022",
          "27/10/2022 to 28/11/2022 - Delivered on 21/12/2022",
          "23/11/2022 to 16/12/2022 - Delivered on 8/12/2022",
          "22/11/2022 to 16/12/2022 - Delivered on 19/12/2022"
     ],
     "Contract Value": "RM125,090.08"
}